MANIFEST.in
README.md
setup.py
qjson/__init__.py
qjson/qjson.py
qjson/qjson_test.py
qjson.egg-info/PKG-INFO
qjson.egg-info/SOURCES.txt
qjson.egg-info/dependency_links.txt
qjson.egg-info/top_level.txt