Metadata-Version: 1.1
Name: qjson
Version: 0.1.6
Summary: quick and dirty way to convert json string to python object
Home-page: https://github.com/jatsz/qjson
Author: Jerry Chou
Author-email: imjatsz@gmail.com
License: MIT License
Download-URL: https://github.com/jatsz/qjson/tarball/master
Keywords: json
Platform: UNKNOWN
